Metadata-Version: 1.1
Name: TextAugRus
Version: 0.1.0
Summary: Little package for text augmentation
Home-page: https://github.com/comptechaug/textaug
Author: TextAugmentationTeam
Author-email: comptechaugteam@gmail.com
License: MIT
Platform: UNKNOWN
Classifier: Development Status :: 3 - Alpha
Classifier: Intended Audience :: Developers
Classifier: Topic :: Software Development :: Build Tools
Classifier: License :: OSI Approved :: MIT License
Classifier: Programming Language :: Python :: 3.7
Classifier: Programming Language :: Python :: 3.6
